{"v":3,"stories":{"example-introduction--page":{"id":"example-introduction--page","title":"Example/Introduction","name":"Page","importPath":"./src/stories/Introduction.stories.mdx"},"components-button--default":{"id":"components-button--default","title":"Components/Button","name":"Default","importPath":"./src/components/Button/Button.stories.tsx"},"components-button--disabled":{"id":"components-button--disabled","title":"Components/Button","name":"Disabled","importPath":"./src/components/Button/Button.stories.tsx"},"components-checkbox--default":{"id":"components-checkbox--default","title":"Components/Checkbox","name":"Default","importPath":"./src/components/Checkbox/Checkbox.stories.tsx"},"components-checkbox--disabled":{"id":"components-checkbox--disabled","title":"Components/Checkbox","name":"Disabled","importPath":"./src/components/Checkbox/Checkbox.stories.tsx"},"components-heading--default":{"id":"components-heading--default","title":"Components/Heading","name":"Default","importPath":"./src/components/Heading/Heading.stories.tsx"},"components-heading--extra-small":{"id":"components-heading--extra-small","title":"Components/Heading","name":"Extra Small","importPath":"./src/components/Heading/Heading.stories.tsx"},"components-heading--small":{"id":"components-heading--small","title":"Components/Heading","name":"Small","importPath":"./src/components/Heading/Heading.stories.tsx"},"components-heading--large":{"id":"components-heading--large","title":"Components/Heading","name":"Large","importPath":"./src/components/Heading/Heading.stories.tsx"},"components-heading--extra-large":{"id":"components-heading--extra-large","title":"Components/Heading","name":"Extra Large","importPath":"./src/components/Heading/Heading.stories.tsx"},"components-heading--color-primary":{"id":"components-heading--color-primary","title":"Components/Heading","name":"Color Primary","importPath":"./src/components/Heading/Heading.stories.tsx"},"components-heading--with-shadow":{"id":"components-heading--with-shadow","title":"Components/Heading","name":"With Shadow","importPath":"./src/components/Heading/Heading.stories.tsx"},"components-heading--custom-component":{"id":"components-heading--custom-component","title":"Components/Heading","name":"Custom Component","importPath":"./src/components/Heading/Heading.stories.tsx"},"components-logo--default":{"id":"components-logo--default","title":"Components/Logo","name":"Default","importPath":"./src/components/Logo/Logo.stories.tsx"},"components-logo--dark":{"id":"components-logo--dark","title":"Components/Logo","name":"Dark","importPath":"./src/components/Logo/Logo.stories.tsx"},"components-switch--default":{"id":"components-switch--default","title":"Components/Switch","name":"Default","importPath":"./src/components/Switch/Switch.stories.tsx"},"components-text--default":{"id":"components-text--default","title":"Components/Text","name":"Default","importPath":"./src/components/Text/Text.stories.tsx"},"components-text--extra-small":{"id":"components-text--extra-small","title":"Components/Text","name":"Extra Small","importPath":"./src/components/Text/Text.stories.tsx"},"components-text--small":{"id":"components-text--small","title":"Components/Text","name":"Small","importPath":"./src/components/Text/Text.stories.tsx"},"components-text--large":{"id":"components-text--large","title":"Components/Text","name":"Large","importPath":"./src/components/Text/Text.stories.tsx"},"components-text--extra-large":{"id":"components-text--extra-large","title":"Components/Text","name":"Extra Large","importPath":"./src/components/Text/Text.stories.tsx"},"components-text--color-primary":{"id":"components-text--color-primary","title":"Components/Text","name":"Color Primary","importPath":"./src/components/Text/Text.stories.tsx"},"components-text--with-shadow":{"id":"components-text--with-shadow","title":"Components/Text","name":"With Shadow","importPath":"./src/components/Text/Text.stories.tsx"},"components-text--custom-component":{"id":"components-text--custom-component","title":"Components/Text","name":"Custom Component","importPath":"./src/components/Text/Text.stories.tsx"},"components-input--default":{"id":"components-input--default","title":"Components/Input","name":"Default","importPath":"./src/components/TextInput/Input.stories.tsx"},"components-input--with-icon":{"id":"components-input--with-icon","title":"Components/Input","name":"With Icon","importPath":"./src/components/TextInput/Input.stories.tsx"},"example-button--primary":{"id":"example-button--primary","title":"Example/Button","name":"Primary","importPath":"./src/stories/Button.stories.tsx"},"example-button--secondary":{"id":"example-button--secondary","title":"Example/Button","name":"Secondary","importPath":"./src/stories/Button.stories.tsx"},"example-button--large":{"id":"example-button--large","title":"Example/Button","name":"Large","importPath":"./src/stories/Button.stories.tsx"},"example-button--small":{"id":"example-button--small","title":"Example/Button","name":"Small","importPath":"./src/stories/Button.stories.tsx"},"example-header--logged-in":{"id":"example-header--logged-in","title":"Example/Header","name":"Logged In","importPath":"./src/stories/Header.stories.tsx"},"example-header--logged-out":{"id":"example-header--logged-out","title":"Example/Header","name":"Logged Out","importPath":"./src/stories/Header.stories.tsx"},"example-page--logged-out":{"id":"example-page--logged-out","title":"Example/Page","name":"Logged Out","importPath":"./src/stories/Page.stories.tsx"},"example-page--logged-in":{"id":"example-page--logged-in","title":"Example/Page","name":"Logged In","importPath":"./src/stories/Page.stories.tsx"}}}
